.gitignore
.travis.yml
LICENSE.txt
MANIFEST.in
README.md
pyproject.toml
setup.cfg
setup.py
tox.ini
data/data_file
src/sample/__init__.py
src/sample/package_data.dat
src/sampleprojectpy2.egg-info/PKG-INFO
src/sampleprojectpy2.egg-info/SOURCES.txt
src/sampleprojectpy2.egg-info/dependency_links.txt
src/sampleprojectpy2.egg-info/entry_points.txt
src/sampleprojectpy2.egg-info/requires.txt
src/sampleprojectpy2.egg-info/top_level.txt
tests/__init__.py
tests/test_simple.py