Metadata-Version: 2.1
Name: sampleprojectpy2
Version: 1.3.1
Summary: A sample Python project
Home-page: https://github.com/pypa/sampleprojectpy2
Author: The Python Packaging Authority
Author-email: pypa-dev@googlegroups.com
License: UNKNOWN
Project-URL: Bug Reports, https://github.com/relrod/sampleprojectpy2/issues
Project-URL: Source, https://github.com/relrod/sampleprojectpy2/
Keywords: sample setuptools development
Platform: UNKNOWN
Classifier: Development Status :: 3 - Alpha
Classifier: Intended Audience :: Developers
Classifier: Topic :: Software Development :: Build Tools
Classifier: License :: OSI Approved :: MIT License
Classifier: Programming Language :: Python :: 2
Classifier: Programming Language :: Python :: 2.7
Classifier: Programming Language :: Python :: 3
Classifier: Programming Language :: Python :: 3.5
Classifier: Programming Language :: Python :: 3.6
Classifier: Programming Language :: Python :: 3.7
Classifier: Programming Language :: Python :: 3.8
Requires-Python: >=2.7, !=3.0.*, !=3.1.*, !=3.2.*, !=3.3.*, !=3.4.*, <4
Provides-Extra: test
Provides-Extra: dev
